ec2connect/__init__.py
ec2connect/console.py
ec2connect/util/__init__.py
ec2connect/util/aws.py
ec2connect/util/config.py
ec2connect/util/saml2aws.py
ec2connect/util/state.py
ec2connect/util/validators.py
ec2connect-2025.6.1.dist-info/licenses/LICENSE.txt
ec2connect-2025.6.1.dist-info/METADATA
ec2connect-2025.6.1.dist-info/WHEEL
ec2connect-2025.6.1.dist-info/entry_points.txt
ec2connect-2025.6.1.dist-info/top_level.txt
ec2connect-2025.6.1.dist-info/RECORD
