Metadata-Version: 2.4
Name: ec2connect
Version: 2025.6.1
Summary: Utility to connect to ec2 instances through a bastion host.
Home-page: https://github.com/goodwillaz/ec2connect
Author: Matt Zuba
Author-email: matt.zuba@goodwillaz.org
License: BSD-3-Clause
Project-URL: Documentation, https://github.com/goodwillaz/ec2connect
Project-URL: Source, https://github.com/goodwillaz/ec2connect
Project-URL: Tracker, https://github.com/goodwillaz/ec2connect/issues
Project-URL: Download, https://pypi.org/project/ec2connect/#files
Platform: any
Classifier: Programming Language :: Python :: 3
Classifier: License :: OSI Approved :: BSD License
Classifier: Operating System :: OS Independent
Requires-Python: >=3.10
License-File: LICENSE.txt
Requires-Dist: packaging<24.0,>=23.0
Requires-Dist: questionary<3.0,>=2.0
Requires-Dist: boto3<2.0,>=1.10.0
Requires-Dist: click<9.0,>=8
Requires-Dist: click-default-group<2.0,>=1.0
Requires-Dist: xdg<7,>=6
Provides-Extra: testing
Requires-Dist: setuptools; extra == "testing"
Requires-Dist: pytest; extra == "testing"
Requires-Dist: pytest-cov; extra == "testing"
Requires-Dist: pyfakefs; extra == "testing"
Provides-Extra: linting
Requires-Dist: pylint; extra == "linting"
Dynamic: license-file
